src/__init__.py
src/__version__.py
src/bitbucket_client.py
src/formatter.py
src/http_server.py
src/models.py
src/server.py
src/settings.py
src/utils.py
src/tools/__init__.py
mcp_server_bitbucket-0.11.0.dist-info/METADATA
mcp_server_bitbucket-0.11.0.dist-info/WHEEL
mcp_server_bitbucket-0.11.0.dist-info/entry_points.txt
mcp_server_bitbucket-0.11.0.dist-info/RECORD
