Metadata-Version: 2.4
Name: mcp-server-bitbucket
Version: 0.11.0
Summary: MCP server for Bitbucket API operations
Project-URL: Homepage, https://github.com/JaviMaligno/mcp-server-bitbucket
Project-URL: Documentation, https://github.com/JaviMaligno/mcp-server-bitbucket#readme
Project-URL: Bug Tracker, https://github.com/JaviMaligno/mcp-server-bitbucket/issues
Project-URL: Repository, https://github.com/JaviMaligno/mcp-server-bitbucket
Author: Javier Aguilar
Keywords: ai,api,bitbucket,claude,mcp
Classifier: Development Status :: 4 - Beta
Classifier: Intended Audience :: Developers
Classifier: License :: OSI Approved :: MIT License
Classifier: Programming Language :: Python :: 3.11
Classifier: Programming Language :: Python :: 3.12
Requires-Python: >=3.11
Requires-Dist: fastapi>=0.115
Requires-Dist: httpx>=0.27
Requires-Dist: mcp>=1.23.1
Requires-Dist: pydantic-settings>=2.0
Requires-Dist: pydantic>=2.0
Requires-Dist: toon-llm>=1.0.0b6
Requires-Dist: uvicorn>=0.32
